dmpdfparser.py
dmpdfparser-1.0.1.dist-info/DESCRIPTION.rst
dmpdfparser-1.0.1.dist-info/METADATA
dmpdfparser-1.0.1.dist-info/RECORD
dmpdfparser-1.0.1.dist-info/WHEEL
dmpdfparser-1.0.1.dist-info/metadata.json
dmpdfparser-1.0.1.dist-info/top_level.txt
